README.txt
setup.py
ai/__init__.py
ai/autoencoder/__init__.py
ai/autoencoder/agn_autoencoder.py
ai/autoencoder/test.py
ai/simple/__init__.py
ai/simple/softmax.py
ai/web/__init__.py
ai/web/api.py
ai_libs.egg-info/PKG-INFO
ai_libs.egg-info/SOURCES.txt
ai_libs.egg-info/dependency_links.txt
ai_libs.egg-info/top_level.txt