Metadata-Version: 1.0
Name: ai-libs
Version: 1.0.0.5
Summary: this is the ai-libs which can help you build the deeplearning quickly
Home-page: http://tikiapp.im
Author: geekbruce
Author-email: bruce.shaoheng@gmail.com
License: UNKNOWN
Platform: UNKNOWN
